{
  "path": "src\\main\\java\\com\\ssafy\\algogo\\program\\group\\service\\GroupService.java",
  "summary": "```json\n{\n  \"language\": \"Java\",\n  \"technologies\": [\n    \"Spring Framework\",\n    \"DTO (Data Transfer Object)\",\n    \"REST API\"\n  ],\n  \"role\": \"GroupService 클래스는 그룹 관련 기능을 제공하는 서비스 계층으로, 그룹 생성, 초대, 멤버 관리, 문제 관리 등의 기능을 수행합니다.\",\n  \"key_features\": [\n    \"그룹 초대 상태 확인 및 관리\",\n    \"그룹 멤버 관리 (역할 업데이트, 삭제)\",\n    \"그룹 문제 추가 및 삭제\",\n    \"그룹 방 목록 조회\",\n    \"내 그룹 방 목록 조회\",\n    \"받은 초대 및 보낸 요청 목록 조회\"\n  ],\n  \"key_code\": [\n    \"void applyGroupInvite(Long programId, ApplyProgramInviteRequestDto applyProgramInviteRequestDto)\",\n    \"void updateGroupInviteState(Long userId, Long programId, Long inviteId, UpdateGroupInviteStateRequestDto updateGroupInviteStateRequestDto)\",\n    \"GetGroupMemberListResponseDto getGroupMember(Long programId)\",\n    \"void addGroupProblem(Long programId, ProgramProblemCreateRequestDto programProblemCreateRequestDto)\",\n    \"ProgramProblemPageResponseDto getAllGroupProblems(Long programId, Pageable pageable)\"\n  ],\n  \"project_hints\": [\n    \"프로그램 관련 그룹 관리 시스템\",\n    \"문제 해결을 위한 그룹 협업 기능\",\n    \"사용자 초대 및 멤버 관리 기능 포함\"\n  ]\n}\n```"
}